clippy_pre_t_x64_win_msvc_nightly_p1/__init__.py
clippy_pre_t_x64_win_msvc_nightly_p1/data/LICENSE-APACHE
clippy_pre_t_x64_win_msvc_nightly_p1/data/LICENSE-MIT
clippy_pre_t_x64_win_msvc_nightly_p1/data/README.md
clippy_pre_t_x64_win_msvc_nightly_p1/data/builder-config
clippy_pre_t_x64_win_msvc_nightly_p1/data/components
clippy_pre_t_x64_win_msvc_nightly_p1/data/git-commit-hash
clippy_pre_t_x64_win_msvc_nightly_p1/data/git-commit-info
clippy_pre_t_x64_win_msvc_nightly_p1/data/install.sh
clippy_pre_t_x64_win_msvc_nightly_p1/data/rust-installer-version
clippy_pre_t_x64_win_msvc_nightly_p1/data/version
clippy_pre_t_x64_win_msvc_nightly_p1/data/clippy-preview/manifest.in
clippy_pre_t_x64_win_msvc_nightly_p1/data/clippy-preview/bin/cargo-clippy.exe
clippy_pre_t_x64_win_msvc_nightly_p1/data/clippy-preview/bin/cargo-clippy.pdb
clippy_pre_t_x64_win_msvc_nightly_p1/data/clippy-preview/bin/clippy-driver.exe
clippy_pre_t_x64_win_msvc_nightly_p1/data/clippy-preview/bin/clippy-driver.pdb
clippy_pre_t_x64_win_msvc_nightly_p1/data/clippy-preview/share/doc/clippy/LICENSE-APACHE
clippy_pre_t_x64_win_msvc_nightly_p1/data/clippy-preview/share/doc/clippy/LICENSE-MIT
clippy_pre_t_x64_win_msvc_nightly_p1/data/clippy-preview/share/doc/clippy/README.md
clippy_pre_t_x64_win_msvc_nightly_p1-0.1.91.dist-info/METADATA
clippy_pre_t_x64_win_msvc_nightly_p1-0.1.91.dist-info/WHEEL
clippy_pre_t_x64_win_msvc_nightly_p1-0.1.91.dist-info/top_level.txt
clippy_pre_t_x64_win_msvc_nightly_p1-0.1.91.dist-info/RECORD
