Metadata-Version: 2.4
Name: clippy_pre_t_x64_win_msvc_nightly_p1
Version: 0.1.91
Summary: Segment clippy-preview.target.x86_64-pc-windows-msvc part p1
License: MIT
